dbt/adapters/fal/__init__.py
dbt/adapters/fal/__version__.py
dbt/adapters/fal/connections.py
dbt/adapters/fal/impl.py
dbt/adapters/fal/load_db_profile.py
dbt/adapters/fal/wrappers.py
dbt/adapters/fal_experimental/__init__.py
dbt/adapters/fal_experimental/__version__.py
dbt/adapters/fal_experimental/adapter.py
dbt/adapters/fal_experimental/adapter_support.py
dbt/adapters/fal_experimental/connections.py
dbt/adapters/fal_experimental/impl.py
dbt/adapters/fal_experimental/support/athena.py
dbt/adapters/fal_experimental/support/bigquery.py
dbt/adapters/fal_experimental/support/duckdb.py
dbt/adapters/fal_experimental/support/postgres.py
dbt/adapters/fal_experimental/support/redshift.py
dbt/adapters/fal_experimental/support/snowflake.py
dbt/adapters/fal_experimental/support/trino.py
dbt/adapters/fal_experimental/telemetry/__init__.py
dbt/adapters/fal_experimental/telemetry/telemetry.py
dbt/adapters/fal_experimental/teleport.py
dbt/adapters/fal_experimental/teleport_adapter_support.py
dbt/adapters/fal_experimental/teleport_support/duckdb.py
dbt/adapters/fal_experimental/teleport_support/snowflake.py
dbt/adapters/fal_experimental/utils/__init__.py
dbt/adapters/fal_experimental/utils/environments.py
dbt/adapters/fal_experimental/utils/yaml_helper.py
dbt/fal/adapters/python/__init__.py
dbt/fal/adapters/python/connections.py
dbt/fal/adapters/python/impl.py
dbt/fal/adapters/teleport/__init__.py
dbt/fal/adapters/teleport/impl.py
dbt/fal/adapters/teleport/info.py
dbt/include/fal/__init__.py
dbt/include/fal/dbt_project.yml
dbt/include/fal/macros/materializations/table.sql
dbt/include/fal/macros/teleport_duckdb.sql
dbt/include/fal/macros/teleport_snowflake.sql
dbt/include/fal_experimental/__init__.py
dbt/include/fal_experimental/dbt_project.yml
dbt/include/fal_experimental/macros/materializations/table.sql
fal/dbt/__init__.py
fal/dbt/cli/__init__.py
fal/dbt/cli/args.py
fal/dbt/cli/cli.py
fal/dbt/cli/dbt_runner.py
fal/dbt/cli/fal_runner.py
fal/dbt/cli/flow_runner.py
dbt_fal-1.5.9.dist-info/METADATA
dbt_fal-1.5.9.dist-info/WHEEL
dbt_fal-1.5.9.dist-info/entry_points.txt
dbt_fal-1.5.9.dist-info/RECORD
