Metadata-Version: 2.1
Name: dbt-fal
Version: 1.5.9
Summary: Run python scripts from any dbt project.
Home-page: https://github.com/fal-ai/fal
Keywords: dbt,pandas,fal,runtime
Author: Features & Labels
Author-email: hello@fal.ai
Requires-Python: >=3.8,<4.0
Classifier: Development Status :: 4 - Beta
Classifier: Programming Language :: Python :: 3
Classifier: Programming Language :: Python :: 3.8
Classifier: Programming Language :: Python :: 3.9
Classifier: Programming Language :: Python :: 3.10
Classifier: Programming Language :: Python :: 3.11
Provides-Extra: athena
Provides-Extra: bigquery
Provides-Extra: duckdb
Provides-Extra: postgres
Provides-Extra: redshift
Provides-Extra: snowflake
Provides-Extra: teleport
Provides-Extra: trino
Requires-Dist: PyYAML (>=6.0,<7.0)
Requires-Dist: agate-sql (>=0.5.8,<0.6.0)
Requires-Dist: astor (>=0.8.1,<0.9.0)
Requires-Dist: awswrangler[redshift] (>=3.0.0) ; (python_version >= "3.8") and (extra == "redshift")
Requires-Dist: backports.functools_lru_cache (>=1.6.4,<2.0.0)
Requires-Dist: dbt-core (>=1.5,<=1.5.5)
Requires-Dist: deprecation (>=2.1.0,<3.0.0)
Requires-Dist: dill (==0.3.7)
Requires-Dist: duckdb-engine (>=0.1.8,<0.2.0) ; extra == "duckdb"
Requires-Dist: fal (>=0.10.0,<0.11.0)
Requires-Dist: google-cloud-bigquery[pandas] (>=3.5.0,<3.6.0) ; extra == "bigquery"
Requires-Dist: importlib-metadata (>=6.0.0,<7.0.0)
Requires-Dist: packaging (>=23)
Requires-Dist: pandas (>=1.3.4,<2.0.0)
Requires-Dist: platformdirs (>=2.5.2,<3.0.0)
Requires-Dist: posthog (>=1.4.5,<2.0.0)
Requires-Dist: s3fs (>=2022.8.2) ; extra == "teleport"
Requires-Dist: snowflake-connector-python[pandas] (>=3.0,<4.0) ; extra == "snowflake"
Requires-Dist: sqlalchemy (>=1.4.41,<2.0.0)
Requires-Dist: sqlalchemy-redshift (>=0.8.9,<0.9.0) ; extra == "redshift"
Requires-Dist: trino[sqlalchemy] (>=0.321.0,<0.322.0) ; extra == "trino"
Requires-Dist: virtualenv (>=20.16.2,<21.0.0)
Project-URL: Repository, https://github.com/fal-ai/fal
